<?xml version="1.0" encoding="utf-8"?>
<Root>
	<Data Level="1" NeedExp="55" OpenRate="1" AwardGold="100" AwardTicket="0" UseTickUp="0" RoomUnlock="0" OneTickUp="5" LevelUpIcon="UI/Image/unlockIcon1.png" AwardItem="0" AwardCount="0" UpType="0" UpRate="0" NeedLucky="0" NeedItems="" NeedCount="" />
	<Data Level="2" NeedExp="137" OpenRate="2" AwardGold="200" AwardTicket="0" UseTickUp="0" RoomUnlock="0" OneTickUp="5" LevelUpIcon="UI/Image/unlockIcon1.png" AwardItem="0" AwardCount="0" UpType="0" UpRate="0" NeedLucky="0" NeedItems="" NeedCount="" />
	<Data Level="3" NeedExp="271" OpenRate="3" AwardGold="225" AwardTicket="0" UseTickUp="0" RoomUnlock="0" OneTickUp="5" LevelUpIcon="UI/Image/unlockIcon1.png" AwardItem="0" AwardCount="0" UpType="0" UpRate="0" NeedLucky="0" NeedItems="" NeedCount="" />
	<Data Level="4" NeedExp="479" OpenRate="4" AwardGold="250" AwardTicket="0" UseTickUp="0" RoomUnlock="0" OneTickUp="10" LevelUpIcon="UI/Image/unlockIcon1.png" AwardItem="0" AwardCount="0" UpType="0" UpRate="0" NeedLucky="0" NeedItems="" NeedCount="" />
	<Data Level="5" NeedExp="782" OpenRate="5" AwardGold="275" AwardTicket="0" UseTickUp="0" RoomUnlock="0" OneTickUp="10" LevelUpIcon="UI/Image/unlockIcon1.png" AwardItem="2" AwardCount="1" UpType="0" UpRate="0" NeedLucky="0" NeedItems="" NeedCount="" />
	<Data Level="6" NeedExp="1203" OpenRate="6" AwardGold="300" AwardTicket="0" UseTickUp="0" RoomUnlock="0" OneTickUp="15" LevelUpIcon="UI/Image/unlockIcon1.png" AwardItem="0" AwardCount="0" UpType="0" UpRate="0" NeedLucky="0" NeedItems="" NeedCount="" />
	<Data Level="7" NeedExp="1762" OpenRate="7" AwardGold="325" AwardTicket="0" UseTickUp="0" RoomUnlock="0" OneTickUp="15" LevelUpIcon="UI/Image/unlockIcon1.png" AwardItem="0" AwardCount="0" UpType="0" UpRate="0" NeedLucky="0" NeedItems="" NeedCount="" />
	<Data Level="8" NeedExp="2479" OpenRate="8" AwardGold="350" AwardTicket="0" UseTickUp="0" RoomUnlock="0" OneTickUp="15" LevelUpIcon="UI/Image/unlockIcon1.png" AwardItem="0" AwardCount="0" UpType="0" UpRate="0" NeedLucky="0" NeedItems="" NeedCount="" />
	<Data Level="9" NeedExp="3376" OpenRate="9" AwardGold="375" AwardTicket="0" UseTickUp="0" RoomUnlock="0" OneTickUp="25" LevelUpIcon="UI/Image/unlockIcon1.png" AwardItem="0" AwardCount="0" UpType="0" UpRate="0" NeedLucky="0" NeedItems="" NeedCount="" />
	<Data Level="10" NeedExp="4472" OpenRate="10" AwardGold="400" AwardTicket="0" UseTickUp="0" RoomUnlock="0" OneTickUp="25" LevelUpIcon="UI/Image/unlockIcon1.png" AwardItem="3" AwardCount="1" UpType="0" UpRate="0" NeedLucky="0" NeedItems="" NeedCount="" />
	<Data Level="11" NeedExp="10520" OpenRate="20" AwardGold="500" AwardTicket="0" UseTickUp="0" RoomUnlock="0" OneTickUp="25" LevelUpIcon="UI/Image/unlockIcon2.png" AwardItem="0" AwardCount="0" UpType="0" UpRate="0" NeedLucky="0" NeedItems="" NeedCount="" />
	<Data Level="12" NeedExp="18936" OpenRate="30" AwardGold="650" AwardTicket="0" UseTickUp="0" RoomUnlock="0" OneTickUp="35" LevelUpIcon="UI/Image/unlockIcon2.png" AwardItem="0" AwardCount="0" UpType="0" UpRate="0" NeedLucky="0" NeedItems="" NeedCount="" />
	<Data Level="13" NeedExp="30298" OpenRate="40" AwardGold="800" AwardTicket="0" UseTickUp="0" RoomUnlock="0" OneTickUp="35" LevelUpIcon="UI/Image/unlockIcon2.png" AwardItem="0" AwardCount="0" UpType="0" UpRate="0" NeedLucky="0" NeedItems="" NeedCount="" />
	<Data Level="14" NeedExp="45447" OpenRate="50" AwardGold="950" AwardTicket="0" UseTickUp="0" RoomUnlock="0" OneTickUp="35" LevelUpIcon="UI/Image/unlockIcon2.png" AwardItem="0" AwardCount="0" UpType="0" UpRate="0" NeedLucky="0" NeedItems="" NeedCount="" />
	<Data Level="15" NeedExp="65444" OpenRate="60" AwardGold="1100" AwardTicket="0" UseTickUp="0" RoomUnlock="0" OneTickUp="45" LevelUpIcon="UI/Image/unlockIcon2.png" AwardItem="0" AwardCount="0" UpType="0" UpRate="0" NeedLucky="0" NeedItems="" NeedCount="" />
	<Data Level="16" NeedExp="91622" OpenRate="70" AwardGold="1250" AwardTicket="0" UseTickUp="0" RoomUnlock="0" OneTickUp="45" LevelUpIcon="UI/Image/unlockIcon2.png" AwardItem="0" AwardCount="0" UpType="0" UpRate="0" NeedLucky="0" NeedItems="" NeedCount="" />
	<Data Level="17" NeedExp="125653" OpenRate="80" AwardGold="1400" AwardTicket="0" UseTickUp="0" RoomUnlock="0" OneTickUp="45" LevelUpIcon="UI/Image/unlockIcon2.png" AwardItem="0" AwardCount="0" UpType="0" UpRate="0" NeedLucky="0" NeedItems="" NeedCount="" />
	<Data Level="18" NeedExp="169631" OpenRate="90" AwardGold="1500" AwardTicket="0" UseTickUp="0" RoomUnlock="0" OneTickUp="60" LevelUpIcon="UI/Image/unlockIcon2.png" AwardItem="0" AwardCount="0" UpType="0" UpRate="0" NeedLucky="0" NeedItems="" NeedCount="" />
	<Data Level="19" NeedExp="208063" OpenRate="100" AwardGold="3000" AwardTicket="0" UseTickUp="400" RoomUnlock="2" OneTickUp="100" LevelUpIcon="UI/Image/unlockIcon2.png" AwardItem="0" AwardCount="0" UpType="0" UpRate="0" NeedLucky="0" NeedItems="" NeedCount="" />
	<Data Level="20" NeedExp="342897" OpenRate="150" AwardGold="4500" AwardTicket="0" UseTickUp="0" RoomUnlock="0" OneTickUp="100" LevelUpIcon="UI/Image/unlockIcon3.png" AwardItem="0" AwardCount="0" UpType="0" UpRate="0" NeedLucky="0" NeedItems="" NeedCount="" />
	<Data Level="21" NeedExp="500156" OpenRate="200" AwardGold="6000" AwardTicket="0" UseTickUp="0" RoomUnlock="0" OneTickUp="100" LevelUpIcon="UI/Image/unlockIcon3.png" AwardItem="0" AwardCount="0" UpType="0" UpRate="0" NeedLucky="0" NeedItems="" NeedCount="" />
	<Data Level="22" NeedExp="681247" OpenRate="250" AwardGold="7500" AwardTicket="0" UseTickUp="0" RoomUnlock="0" OneTickUp="125" LevelUpIcon="UI/Image/unlockIcon3.png" AwardItem="0" AwardCount="0" UpType="0" UpRate="0" NeedLucky="0" NeedItems="" NeedCount="" />
	<Data Level="23" NeedExp="887569" OpenRate="300" AwardGold="9000" AwardTicket="0" UseTickUp="0" RoomUnlock="0" OneTickUp="125" LevelUpIcon="UI/Image/unlockIcon3.png" AwardItem="0" AwardCount="0" UpType="0" UpRate="0" NeedLucky="0" NeedItems="" NeedCount="" />
	<Data Level="24" NeedExp="1120510" OpenRate="350" AwardGold="10500" AwardTicket="0" UseTickUp="0" RoomUnlock="0" OneTickUp="150" LevelUpIcon="UI/Image/unlockIcon3.png" AwardItem="0" AwardCount="0" UpType="0" UpRate="0" NeedLucky="0" NeedItems="" NeedCount="" />
	<Data Level="25" NeedExp="1381454" OpenRate="400" AwardGold="12000" AwardTicket="0" UseTickUp="0" RoomUnlock="0" OneTickUp="150" LevelUpIcon="UI/Image/unlockIcon3.png" AwardItem="0" AwardCount="0" UpType="0" UpRate="0" NeedLucky="0" NeedItems="" NeedCount="" />
	<Data Level="26" NeedExp="1671777" OpenRate="450" AwardGold="13500" AwardTicket="0" UseTickUp="0" RoomUnlock="0" OneTickUp="175" LevelUpIcon="UI/Image/unlockIcon3.png" AwardItem="0" AwardCount="0" UpType="0" UpRate="0" NeedLucky="0" NeedItems="" NeedCount="" />
	<Data Level="27" NeedExp="1992846" OpenRate="500" AwardGold="15000" AwardTicket="0" UseTickUp="0" RoomUnlock="0" OneTickUp="175" LevelUpIcon="UI/Image/unlockIcon3.png" AwardItem="0" AwardCount="0" UpType="0" UpRate="0" NeedLucky="0" NeedItems="" NeedCount="" />
	<Data Level="28" NeedExp="2346024" OpenRate="550" AwardGold="16500" AwardTicket="0" UseTickUp="0" RoomUnlock="0" OneTickUp="200" LevelUpIcon="UI/Image/unlockIcon3.png" AwardItem="0" AwardCount="0" UpType="0" UpRate="0" NeedLucky="0" NeedItems="" NeedCount="" />
	<Data Level="29" NeedExp="2732668" OpenRate="600" AwardGold="18000" AwardTicket="0" UseTickUp="0" RoomUnlock="0" OneTickUp="200" LevelUpIcon="UI/Image/unlockIcon3.png" AwardItem="0" AwardCount="0" UpType="0" UpRate="0" NeedLucky="0" NeedItems="" NeedCount="" />
	<Data Level="30" NeedExp="3154127" OpenRate="650" AwardGold="19500" AwardTicket="0" UseTickUp="0" RoomUnlock="0" OneTickUp="225" LevelUpIcon="UI/Image/unlockIcon3.png" AwardItem="0" AwardCount="0" UpType="0" UpRate="0" NeedLucky="0" NeedItems="" NeedCount="" />
	<Data Level="31" NeedExp="3611747" OpenRate="700" AwardGold="21000" AwardTicket="0" UseTickUp="0" RoomUnlock="0" OneTickUp="225" LevelUpIcon="UI/Image/unlockIcon3.png" AwardItem="0" AwardCount="0" UpType="0" UpRate="0" NeedLucky="0" NeedItems="" NeedCount="" />
	<Data Level="32" NeedExp="4106866" OpenRate="750" AwardGold="22500" AwardTicket="0" UseTickUp="0" RoomUnlock="0" OneTickUp="250" LevelUpIcon="UI/Image/unlockIcon3.png" AwardItem="0" AwardCount="0" UpType="0" UpRate="0" NeedLucky="0" NeedItems="" NeedCount="" />
	<Data Level="33" NeedExp="4640820" OpenRate="800" AwardGold="24000" AwardTicket="0" UseTickUp="0" RoomUnlock="0" OneTickUp="250" LevelUpIcon="UI/Image/unlockIcon3.png" AwardItem="0" AwardCount="0" UpType="0" UpRate="0" NeedLucky="0" NeedItems="" NeedCount="" />
	<Data Level="34" NeedExp="5214937" OpenRate="850" AwardGold="25500" AwardTicket="0" UseTickUp="0" RoomUnlock="0" OneTickUp="275" LevelUpIcon="UI/Image/unlockIcon3.png" AwardItem="0" AwardCount="0" UpType="0" UpRate="0" NeedLucky="0" NeedItems="" NeedCount="" />
	<Data Level="35" NeedExp="5830542" OpenRate="900" AwardGold="27000" AwardTicket="0" UseTickUp="0" RoomUnlock="0" OneTickUp="275" LevelUpIcon="UI/Image/unlockIcon3.png" AwardItem="0" AwardCount="0" UpType="0" UpRate="0" NeedLucky="0" NeedItems="" NeedCount="" />
	<Data Level="36" NeedExp="6488955" OpenRate="950" AwardGold="28500" AwardTicket="0" UseTickUp="0" RoomUnlock="0" OneTickUp="300" LevelUpIcon="UI/Image/unlockIcon3.png" AwardItem="0" AwardCount="0" UpType="0" UpRate="0" NeedLucky="0" NeedItems="" NeedCount="" />
	<Data Level="37" NeedExp="0" OpenRate="1000" AwardGold="30000" AwardTicket="0" UseTickUp="900" RoomUnlock="3" OneTickUp="0" LevelUpIcon="UI/Image/unlockIcon3.png" AwardItem="0" AwardCount="0" UpType="1" UpRate="10000" NeedLucky="20" NeedItems="60,62,63,61" NeedCount="10,10,10,10" />
	<Data Level="38" NeedExp="0" OpenRate="1200" AwardGold="1000" AwardTicket="0" UseTickUp="0" RoomUnlock="0" OneTickUp="0" LevelUpIcon="UI/Image/unlockIcon3.png" AwardItem="0" AwardCount="0" UpType="1" UpRate="6667" NeedLucky="30" NeedItems="60,62,63,61" NeedCount="20,20,20,20" />
	<Data Level="39" NeedExp="0" OpenRate="1400" AwardGold="1000" AwardTicket="0" UseTickUp="0" RoomUnlock="0" OneTickUp="0" LevelUpIcon="UI/Image/unlockIcon3.png" AwardItem="0" AwardCount="0" UpType="1" UpRate="6000" NeedLucky="40" NeedItems="60,62,63,61" NeedCount="30,30,30,30" />
	<Data Level="40" NeedExp="0" OpenRate="1600" AwardGold="1000" AwardTicket="0" UseTickUp="0" RoomUnlock="0" OneTickUp="0" LevelUpIcon="UI/Image/unlockIcon3.png" AwardItem="0" AwardCount="0" UpType="1" UpRate="4000" NeedLucky="50" NeedItems="60,62,63,61" NeedCount="40,40,40,40" />
	<Data Level="41" NeedExp="0" OpenRate="1800" AwardGold="1000" AwardTicket="0" UseTickUp="0" RoomUnlock="0" OneTickUp="0" LevelUpIcon="UI/Image/unlockIcon3.png" AwardItem="0" AwardCount="0" UpType="1" UpRate="3333" NeedLucky="60" NeedItems="60,62,63,61" NeedCount="50,50,50,50" />
	<Data Level="42" NeedExp="0" OpenRate="2000" AwardGold="1000" AwardTicket="0" UseTickUp="0" RoomUnlock="0" OneTickUp="0" LevelUpIcon="UI/Image/unlockIcon3.png" AwardItem="0" AwardCount="0" UpType="1" UpRate="3000" NeedLucky="70" NeedItems="60,62,63,61" NeedCount="60,60,60,60" />
	<Data Level="43" NeedExp="0" OpenRate="2300" AwardGold="1000" AwardTicket="0" UseTickUp="0" RoomUnlock="0" OneTickUp="0" LevelUpIcon="UI/Image/unlockIcon3.png" AwardItem="0" AwardCount="0" UpType="1" UpRate="2333" NeedLucky="80" NeedItems="60,62,63,61" NeedCount="70,70,70,70" />
	<Data Level="44" NeedExp="0" OpenRate="2600" AwardGold="1000" AwardTicket="0" UseTickUp="0" RoomUnlock="0" OneTickUp="0" LevelUpIcon="UI/Image/unlockIcon3.png" AwardItem="0" AwardCount="0" UpType="1" UpRate="2000" NeedLucky="100" NeedItems="60,62,63,61" NeedCount="80,80,80,80" />
	<Data Level="45" NeedExp="0" OpenRate="3000" AwardGold="1000" AwardTicket="0" UseTickUp="0" RoomUnlock="0" OneTickUp="0" LevelUpIcon="UI/Image/unlockIcon3.png" AwardItem="0" AwardCount="0" UpType="1" UpRate="1636" NeedLucky="120" NeedItems="60,62,63,61" NeedCount="90,90,90,90" />
	<Data Level="46" NeedExp="0" OpenRate="3500" AwardGold="1000" AwardTicket="0" UseTickUp="0" RoomUnlock="0" OneTickUp="0" LevelUpIcon="UI/Image/unlockIcon3.png" AwardItem="0" AwardCount="0" UpType="1" UpRate="1667" NeedLucky="120" NeedItems="60,62,63,61" NeedCount="100,100,100,100" />
	<Data Level="47" NeedExp="0" OpenRate="4000" AwardGold="1000" AwardTicket="0" UseTickUp="0" RoomUnlock="0" OneTickUp="0" LevelUpIcon="UI/Image/unlockIcon3.png" AwardItem="0" AwardCount="0" UpType="1" UpRate="1571" NeedLucky="130" NeedItems="60,62,63,61" NeedCount="110,110,110,110" />
	<Data Level="48" NeedExp="0" OpenRate="4500" AwardGold="1000" AwardTicket="0" UseTickUp="0" RoomUnlock="0" OneTickUp="0" LevelUpIcon="UI/Image/unlockIcon3.png" AwardItem="0" AwardCount="0" UpType="1" UpRate="1333" NeedLucky="150" NeedItems="60,62,63,61" NeedCount="120,120,120,120" />
	<Data Level="49" NeedExp="0" OpenRate="5000" AwardGold="1000" AwardTicket="0" UseTickUp="0" RoomUnlock="0" OneTickUp="0" LevelUpIcon="UI/Image/unlockIcon3.png" AwardItem="0" AwardCount="0" UpType="1" UpRate="0" NeedLucky="0" NeedItems="60,62,63,61" NeedCount="130,130,130,130" />
</Root>